rangeflow/__init__.py
rangeflow/advanced_train.py
rangeflow/analysis.py
rangeflow/backend.py
rangeflow/continual.py
rangeflow/core.py
rangeflow/functional.py
rangeflow/layers.py
rangeflow/linear_bounds.py
rangeflow/loss.py
rangeflow/metrics.py
rangeflow/nlp.py
rangeflow/ops.py
rangeflow/optim.py
rangeflow/patch.py
rangeflow/quantization.py
rangeflow/rl.py
rangeflow/timeseries.py
rangeflow/train.py
rangeflow/transforms.py
rangeflow/utils.py
rangeflow/verification.py
rangeflow/vision.py
rangeflow/visualize.py
rangeflow-0.5.0.dist-info/licenses/LICENSE
rangeflow-0.5.0.dist-info/METADATA
rangeflow-0.5.0.dist-info/WHEEL
rangeflow-0.5.0.dist-info/top_level.txt
rangeflow-0.5.0.dist-info/RECORD
