Metadata-Version: 2.4
Name: rangeflow
Version: 0.5.0
Summary: Certified Robustness and Uncertainty Quantification for AI
Author-email: Dheeren Tejani <dheerenntejani@gmail.com>
License: MIT
Project-URL: Homepage, https://github.com/dheeren-tejani/rangeflow
Project-URL: Bug Tracker, https://github.com/dheeren-tejani/rangeflow/issues
Project-URL: Documentation, https://github.com/dheeren-tejani/rangeflow#readme
Project-URL: Source Code, https://github.com/dheeren-tejani/rangeflow
Keywords: machine-learning,robustness,uncertainty,interval-arithmetic,ai-safety
Classifier: Development Status :: 4 - Beta
Classifier: Intended Audience :: Science/Research
Classifier: Intended Audience :: Developers
Classifier: License :: OSI Approved :: MIT License
Classifier: Programming Language :: Python :: 3
Classifier: Programming Language :: Python :: 3.8
Classifier: Programming Language :: Python :: 3.9
Classifier: Programming Language :: Python :: 3.10
Classifier: Programming Language :: Python :: 3.11
Classifier: Programming Language :: Python :: 3.12
Classifier: Topic :: Scientific/Engineering :: Artificial Intelligence
Classifier: Topic :: Scientific/Engineering :: Mathematics
Classifier: Topic :: Software Development :: Libraries :: Python Modules
Requires-Python: >=3.8
License-File: LICENSE
Requires-Dist: numpy>=1.19.0
Provides-Extra: gpu
Requires-Dist: cupy-cuda12x>=12.0.0; extra == "gpu"
Provides-Extra: torch
Requires-Dist: torch>=2.0.0; extra == "torch"
Provides-Extra: viz
Requires-Dist: matplotlib>=3.3.0; extra == "viz"
Provides-Extra: all
Requires-Dist: torch>=2.0.0; extra == "all"
Requires-Dist: matplotlib>=3.3.0; extra == "all"
Requires-Dist: cupy-cuda12x>=12.0.0; extra == "all"
Provides-Extra: dev
Requires-Dist: pytest>=7.0.0; extra == "dev"
Requires-Dist: pytest-cov>=4.0.0; extra == "dev"
Requires-Dist: black>=22.0.0; extra == "dev"
Requires-Dist: flake8>=5.0.0; extra == "dev"
Requires-Dist: mypy>=0.990; extra == "dev"
Requires-Dist: colorama>=0.4.0; extra == "dev"
Provides-Extra: docs
Requires-Dist: sphinx>=5.0.0; extra == "docs"
Requires-Dist: sphinx-rtd-theme>=1.0.0; extra == "docs"
Dynamic: license-file
